pygasflow/__init__.py
pygasflow/_version.py
pygasflow/common.py
pygasflow/fanno.py
pygasflow/generic.py
pygasflow/isentropic.py
pygasflow/rayleigh.py
pygasflow/shockwave.py
pygasflow/atd/__init__.py
pygasflow/atd/nd_numbers.py
pygasflow/atd/temperatures.py
pygasflow/atd/thermal_conductivity.py
pygasflow/atd/viscosity.py
pygasflow/atd/viscous_interaction.py
pygasflow/atd/avf/__init__.py
pygasflow/atd/avf/heat_flux_fp.py
pygasflow/atd/avf/heat_flux_sp.py
pygasflow/atd/avf/thickness_fp.py
pygasflow/atd/avf/wall_shear_stress_fp.py
pygasflow/atd/avf/wall_shear_stress_sp.py
pygasflow/atd/newton/__init__.py
pygasflow/atd/newton/elliptic_cone.py
pygasflow/atd/newton/pressures.py
pygasflow/atd/newton/sharp_cone.py
pygasflow/atd/newton/sphere.py
pygasflow/atd/newton/utils.py
pygasflow/data/m-beta-theta_c-g1.05.csv.zip
pygasflow/data/m-beta-theta_c-g1.1.csv.zip
pygasflow/data/m-beta-theta_c-g1.15.csv.zip
pygasflow/data/m-beta-theta_c-g1.2.csv.zip
pygasflow/data/m-beta-theta_c-g1.25.csv.zip
pygasflow/data/m-beta-theta_c-g1.3.csv.zip
pygasflow/data/m-beta-theta_c-g1.35.csv.zip
pygasflow/data/m-beta-theta_c-g1.4.csv.zip
pygasflow/data/m-beta-theta_c-g1.45.csv.zip
pygasflow/data/m-beta-theta_c-g1.5.csv.zip
pygasflow/data/m-beta-theta_c-g1.55.csv.zip
pygasflow/data/m-beta-theta_c-g1.6.csv.zip
pygasflow/data/m-beta-theta_c-g1.65.csv.zip
pygasflow/data/m-beta-theta_c-g1.7.csv.zip
pygasflow/data/m-beta-theta_c-g1.75.csv.zip
pygasflow/data/m-beta-theta_c-g1.8.csv.zip
pygasflow/data/m-beta-theta_c-g1.85.csv.zip
pygasflow/data/m-beta-theta_c-g1.9.csv.zip
pygasflow/data/m-beta-theta_c-g1.95.csv.zip
pygasflow/data/m-beta-theta_c-g2.csv.zip
pygasflow/interactive/__init__.py
pygasflow/interactive/compressible.py
pygasflow/interactive/diagrams/__init__.py
pygasflow/interactive/diagrams/conical_shock.py
pygasflow/interactive/diagrams/de_laval.py
pygasflow/interactive/diagrams/fanno.py
pygasflow/interactive/diagrams/flow_base.py
pygasflow/interactive/diagrams/gas.py
pygasflow-1.4.0.dist-info/licenses/LICENSE
pygasflow-1.4.0.dist-info/METADATA
pygasflow-1.4.0.dist-info/WHEEL
pygasflow-1.4.0.dist-info/top_level.txt
pygasflow-1.4.0.dist-info/RECORD
